ocean_crow_voting_system/__init__.py
ocean_crow_voting_system/main.py
ocean_crow_voting_system/ocean_crow_voting_system.py
ocean_crow_voting_system-0.1.0.dist-info/licenses/LICENSE
ocean_crow_voting_system-0.1.0.dist-info/METADATA
ocean_crow_voting_system-0.1.0.dist-info/WHEEL
ocean_crow_voting_system-0.1.0.dist-info/top_level.txt
ocean_crow_voting_system-0.1.0.dist-info/RECORD
