Metadata-Version: 2.4
Name: ocean-crow-voting-system
Version: 0.1.0
Summary: A voting system package
Author-email: Sheldon Kenny Salmon <OceanCrowtt@gmail.com>
License-Expression: MIT
License-File: LICENSE
Requires-Dist: pygame>=2.0.0
Dynamic: license-file
